{
  "forge_marker": 1,
  "defaults": {
    "model": "zhenzimod:iron_lightning_block_broken"
  },
  "variants": {
    "facing=south": {"model": "zhenzimod:iron_lightning_block_broken", "y": 180, "uvlock": false},
    "facing=north": {"model": "zhenzimod:iron_lightning_block_broken"},
    "facing=east": {"model": "zhenzimod:iron_lightning_block_broken", "y": 90, "uvlock": false},
    "facing=west": {"model": "zhenzimod:iron_lightning_block_broken", "y": 270, "uvlock": false},
    "normal": [{}],
    "inventory": [{}]
  }
}